nightshade/__init__.py
nightshade/csv.py
nightshade/models.py
nightshade/notion.py
nightshade/rottentomatoes.py
nightshade/search.py
nightshade/util.py
nightshade-0.1.0.dist-info/entry_points.txt
nightshade-0.1.0.dist-info/LICENSE
nightshade-0.1.0.dist-info/WHEEL
nightshade-0.1.0.dist-info/METADATA
nightshade-0.1.0.dist-info/RECORD
